Metadata-Version: 2.1
Name: yamtable
Version: 0.0.1
Summary: A yaml-table mashup
Home-page: https://github.com/beasteers/yamtable
Author: Bea Steers
Author-email: bea.steers@gmail.com
License: MIT License
Keywords: yaml table mix tabular tabulate nested dict inside
Platform: UNKNOWN
